bidsschematools-1.1.5.dist-info/METADATA
bidsschematools-1.1.5.dist-info/WHEEL
bidsschematools-1.1.5.dist-info/entry_points.txt
bidsschematools-1.1.5.dist-info/licenses/LICENSE
bidsschematools/__init__.py
bidsschematools/__main__.py
bidsschematools/_lazytypes.py
bidsschematools/_version.py
bidsschematools/conftest.py
bidsschematools/data/__init__.py
bidsschematools/data/metaschema.json
bidsschematools/data/schema.json
bidsschematools/data/tests/test_rules.py
bidsschematools/expressions.py
bidsschematools/py.typed
bidsschematools/render/__init__.py
bidsschematools/render/tables.py
bidsschematools/render/text.py
bidsschematools/render/tsv.py
bidsschematools/render/utils.py
bidsschematools/rules.py
bidsschematools/schema.py
bidsschematools/tests/__init__.py
bidsschematools/tests/data/__init__.py
bidsschematools/tests/data/broken_dataset_description.json
bidsschematools/tests/data/expected_bids_validator_xs_write.log
bidsschematools/tests/test_expressions.py
bidsschematools/tests/test_make_testdata.py
bidsschematools/tests/test_render_tables.py
bidsschematools/tests/test_render_text.py
bidsschematools/tests/test_render_utils.py
bidsschematools/tests/test_rules.py
bidsschematools/tests/test_schema.py
bidsschematools/tests/test_utils.py
bidsschematools/tests/test_validator.py
bidsschematools/types/__init__.py
bidsschematools/types/context.py
bidsschematools/types/namespace.py
bidsschematools/types/protocols.py
bidsschematools/utils.py
bidsschematools/validator.py
bidsschematools-1.1.5.dist-info/RECORD
